imputena/__init__.py
imputena/deletion/__init__.py
imputena/deletion/delete_columns.py
imputena/deletion/delete_listwise.py
imputena/deletion/delete_pairwise.py
imputena/multiple_imputation/__init__.py
imputena/multiple_imputation/mice.py
imputena/multiple_imputation/srmi.py
imputena/recommendation/__init__.py
imputena/recommendation/get_applicable_methods.py
imputena/recommendation/impute_by_recommended.py
imputena/recommendation/recommend_method.py
imputena/recommendation/utils.py
imputena/simple_imputation/__init__.py
imputena/simple_imputation/constant_value_imputation.py
imputena/simple_imputation/interpolation.py
imputena/simple_imputation/knn.py
imputena/simple_imputation/linear_regression.py
imputena/simple_imputation/locf.py
imputena/simple_imputation/logistic_regression.py
imputena/simple_imputation/mean_substitution.py
imputena/simple_imputation/most_frequent.py
imputena/simple_imputation/nocb.py
imputena/simple_imputation/random_hot_deck_imputation.py
imputena/simple_imputation/random_sample_imputation.py
imputena/simple_imputation/random_value_imputation.py
imputena/simple_imputation/seasonal_interpolation.py
test/deletion/__init__.py
test/deletion/test_delete_columns.py
test/deletion/test_delete_listwise.py
test/deletion/test_delete_pairwise.py
test/multiple_imputation/__init__.py
test/multiple_imputation/test_mice.py
test/multiple_imputation/test_srmi.py
test/recommendation/__init__.py
test/recommendation/test_get_applicable_methods.py
test/recommendation/test_impute_by_recommended.py
test/recommendation/test_recommend_method.py
test/simple_imputation/__init__.py
test/simple_imputation/test_constant_value_imputation.py
test/simple_imputation/test_interpolation.py
test/simple_imputation/test_knn.py
test/simple_imputation/test_linear_regression.py
test/simple_imputation/test_locf.py
test/simple_imputation/test_logistic_regression.py
test/simple_imputation/test_mean_substitution.py
test/simple_imputation/test_most_frequent.py
imputena-1.0.dist-info/LICENSE.txt
imputena-1.0.dist-info/METADATA
imputena-1.0.dist-info/WHEEL
imputena-1.0.dist-info/top_level.txt
imputena-1.0.dist-info/RECORD
